{
    "openapi": "3.0.0",
    "info": {
      "title": "Authentication Service API",
      "version": "1.0.0"
    },
    "paths": {
      "/auth/register": {
        "post": {
          "summary": "Register a new user",
          "requestBody": {
            "content": {
              "application/json": {
                "schema": {
                  "type": "object",
                  "properties": {
                    "username": {
                      "type": "string",
                      "description": "The username of the new user"
                    },
                    "password": {
                      "type": "string",
                      "description": "The password of the new user"
                    }
                  },
                  "required": [
                    "username",
                    "password"
                  ]
                }
              }
            }
          },
          "responses": {
            "201": {
              "description": "User registered successfully"
            },
            "400": {
              "description": "Invalid request body or username already exists"
            },
            "500": {
              "description": "Internal server error"
            }
          }
        }
      },
      "/auth/login": {
        "post": {
          "summary": "Login a user",
          "requestBody": {
            "content": {
              "application/json": {
                "schema": {
                  "type": "object",
                  "properties": {
                    "username": {
                      "type": "string",
                      "description": "The username of the user"
                    },
                    "password": {
                      "type": "string",
                      "description": "The password of the user"
                    }
                  },
                  "required": [
                    "username",
                    "password"
                  ]
                }
              }
            }
          },
          "responses": {
            "200": {
              "description": "Login successful",
              "content": {
                "application/json": {
                  "schema": {
                    "type": "object",
                    "properties": {
                      "token": {
                        "type": "string",
                        "description": "The authentication token"
                      }
                    }
                  }
                }
              }
            },
            "400": {
              "description": "Invalid credentials"
            },
            "500": {
              "description": "Internal server error"
            }
          }
        }
      },
      "/users": {
        "get": {
          "summary": "Get all users",
          "security": [
            {
              "bearerAuth": []
            }
          ],
          "responses": {
            "200": {
              "description": "List of users",
              "content": {
                "application/json": {
                  "schema": {
                    "type": "array",
                    "items": {
                      "type": "object",
                      "properties": {
                        "username": {
                          "type": "string"
                        },
                        "password": {
                          "type": "string"
                        }
                      }
                    }
                  }
                }
              }
            },
            "401": {
              "description": "Unauthorized"
            },
            "500": {
              "description": "Internal server error"
            }
          }
        }
      },
      "/existing": {
        "get": {
          "summary": "Protected route",
          "security": [
            {
              "bearerAuth": []
            }
          ],
          "responses": {
            "200": {
              "description": "Success",
              "content": {
                "application/json": {
                  "schema": {
                    "type": "object",
                    "properties": {
                      "message": {
                        "type": "string"
                      },
                      "user": {
                        "type": "object"
                      }
                    }
                  }
                }
              }
            }
          }
        }
      }
    },
    "components": {
      "securitySchemes": {
        "bearerAuth": {
          "type": "http",
          "scheme": "bearer",
          "bearerFormat": "JWT"
        }
      }
    }
  }
  